{"schema_version":1,"id":"00-0031372","profile":{"name":"Bradley Roby","pos":"CB","dob":"1992-05-01","height_in":71,"weight_lb":194,"college":"Ohio State","draft":{"year":2014,"round":1,"pick":31,"team":"DEN"},"headshot":"https://static.www.nfl.com/image/private/f_auto,q_auto/league/b2ef6tlrbcqpdnnolzcq","teams":["DEN","HOU","NO","PHI"]},"seasons":[{"season":2015,"team":"DEN","teams":["DEN"],"pos":"CB","games":16,"game_type":"REG","stats":{"tackles_solo":32,"tackles":38,"tfl":1,"def_int":1,"pass_defended":10,"ff":1,"fr":1,"def_td":1,"snaps":623,"snap_share":0.576},"percentiles":{"tackles_solo":25.5,"tackles":22.8,"tfl":50.0,"def_int":50.0,"pass_defended":75.0,"ff":75.0,"fr":75.0,"def_td":95.0,"snaps":30.5,"snap_share":18.6}},{"season":2015,"team":"DEN","teams":["DEN"],"pos":"CB","games":3,"game_type":"POST","stats":{"tackles_solo":5,"tackles":5,"pass_defended":3,"ff":1,"snaps":164,"snap_share":0.732},"percentiles":{}},{"season":2016,"team":"DEN","teams":["DEN"],"pos":"DB","games":16,"game_type":"REG","stats":{"tackles_solo":33,"tackles":38,"def_sacks":1.0,"def_int":2,"pass_defended":8,"ff":1,"def_td":2,"snaps":688,"snap_share":0.605},"percentiles":{"tackles_solo":32.4,"tackles":24.4,"def_sacks":75.0,"def_int":75.0,"pass_defended":58.3,"ff":75.0,"def_td":95.0,"snaps":46.5,"snap_share":21.9}},{"season":2017,"team":"DEN","teams":["DEN"],"pos":"DB","games":16,"game_type":"REG","stats":{"tackles_solo":35,"tackles":42,"tfl":1,"def_sacks":1.0,"qb_hits":1,"def_int":1,"pass_defended":17,"ff":1,"fr":1,"snaps":674,"snap_share":0.687},"percentiles":{"tackles_solo":45.2,"tackles":39.1,"tfl":41.7,"def_sacks":90.0,"qb_hits":75.0,"def_int":50.0,"pass_defended":94.2,"ff":75.0,"fr":75.0,"snaps":46.1,"snap_share":29.0}},{"season":2018,"team":"DEN","teams":["DEN"],"pos":"DB","games":15,"game_type":"REG","stats":{"tackles_solo":43,"tackles":48,"tfl":1,"def_int":1,"pass_defended":12,"ff":2,"snaps":926,"snap_share":0.912},"percentiles":{"tackles_solo":58.3,"tackles":49.1,"tfl":50.0,"def_int":50.0,"pass_defended":87.2,"ff":95.0,"snaps":72.3,"snap_share":65.3}},{"season":2019,"team":"HOU","teams":["HOU"],"pos":"DB","games":10,"game_type":"REG","stats":{"tackles_solo":34,"tackles":37,"tfl":2,"def_sacks":1.0,"qb_hits":1,"def_int":2,"pass_defended":8,"ff":1,"def_td":1,"snaps":655,"snap_share":0.955},"percentiles":{"tackles_solo":50.0,"tackles":30.8,"tfl":62.5,"def_sacks":75.0,"qb_hits":75.0,"def_int":75.0,"pass_defended":75.0,"ff":75.0,"def_td":95.0,"snaps":46.5,"snap_share":74.6}},{"season":2019,"team":"HOU","teams":["HOU"],"pos":"DB","games":2,"game_type":"POST","stats":{"tackles_solo":11,"tackles":11,"pass_defended":2,"snaps":146,"snap_share":1.0},"percentiles":{}},{"season":2020,"team":"HOU","teams":["HOU"],"pos":"DB","games":10,"game_type":"REG","stats":{"tackles_solo":31,"tackles":35,"tfl":2,"def_int":1,"pass_defended":7,"fr":1,"snaps":613,"snap_share":0.87},"percentiles":{"tackles_solo":35.9,"tackles":25.0,"tfl":75.0,"def_int":50.0,"pass_defended":66.7,"fr":75.0,"snaps":41.2,"snap_share":57.4}},{"season":2021,"team":"NO","teams":["NO"],"pos":"DB","games":14,"game_type":"REG","stats":{"tackles_solo":19,"tackles":23,"tfl":3,"def_sacks":1.0,"qb_hits":3,"def_int":1,"pass_defended":5,"snaps":394,"snap_share":0.415},"percentiles":{"tackles_solo":15.3,"tackles":11.2,"tfl":75.0,"def_sacks":90.0,"qb_hits":90.0,"def_int":50.0,"pass_defended":50.0,"snaps":23.5,"snap_share":8.3}},{"season":2022,"team":"NO","teams":["NO"],"pos":"DB","games":13,"game_type":"REG","stats":{"tackles_solo":28,"tackles":35,"tfl":1,"pass_defended":5,"fr":2,"snaps":628,"snap_share":0.732},"percentiles":{"tackles_solo":32.5,"tackles":25.7,"tfl":50.0,"pass_defended":41.7,"fr":95.0,"snaps":39.5,"snap_share":25.0}},{"season":2023,"team":"PHI","teams":["PHI"],"pos":"DB","games":9,"game_type":"REG","stats":{"tackles_solo":18,"tackles":21,"tfl":2,"qb_hits":1,"ff":1,"snaps":344,"snap_share":0.549},"percentiles":{"tackles_solo":12.1,"tackles":6.2,"tfl":62.5,"qb_hits":75.0,"ff":75.0,"snaps":13.3,"snap_share":20.9}},{"season":2023,"team":"PHI","teams":["PHI"],"pos":"DB","games":1,"game_type":"POST","stats":{"tackles_solo":2,"tackles":3,"snaps":35,"snap_share":0.5},"percentiles":{}}],"career":{"games":119,"stats":{"tackles_solo":273,"tackles":317,"tfl":13,"def_int":9,"pass_defended":72,"ff":7,"fr":5,"def_td":4,"snaps":5545,"def_sacks":4.0,"qb_hits":6}},"career_post":{"games":6,"stats":{"tackles_solo":18,"tackles":19,"pass_defended":5,"ff":1,"snaps":345}},"game_logs":[{"season":2015,"week":1,"game_type":"REG","date":"2015-09-13","team":"DEN","opp":"BAL","home":true,"stats":{"tackles":1,"pass_defended":1}},{"season":2015,"week":2,"game_type":"REG","date":"2015-09-17","team":"DEN","opp":"KC","home":false,"stats":{"fr":1,"def_td":1}},{"season":2015,"week":3,"game_type":"REG","date":"2015-09-27","team":"DEN","opp":"DET","home":false,"stats":{"tackles_solo":2,"tackles":2,"def_int":1,"pass_defended":1}},{"season":2015,"week":4,"game_type":"REG","date":"2015-10-04","team":"DEN","opp":"MIN","home":true,"stats":{"tackles_solo":5,"tackles":5,"pass_defended":1,"ff":1}},{"season":2015,"week":5,"game_type":"REG","date":"2015-10-11","team":"DEN","opp":"LV","home":false,"stats":{"tackles_solo":2,"tackles":3}},{"season":2015,"week":6,"game_type":"REG","date":"2015-10-18","team":"DEN","opp":"CLE","home":false,"stats":{"tackles_solo":2,"tackles":2}},{"season":2015,"week":8,"game_type":"REG","date":"2015-11-01","team":"DEN","opp":"GB","home":true,"stats":{"tackles":1}},{"season":2015,"week":9,"game_type":"REG","date":"2015-11-08","team":"DEN","opp":"IND","home":false,"stats":{"tackles_solo":2,"tackles":4,"pass_defended":1}},{"season":2015,"week":10,"game_type":"REG","date":"2015-11-15","team":"DEN","opp":"KC","home":true,"stats":{"tackles_solo":4,"tackles":4}},{"season":2015,"week":11,"game_type":"REG","date":"2015-11-22","team":"DEN","opp":"CHI","home":false,"stats":{"tackles_solo":1,"tackles":2,"pass_defended":2}},{"season":2015,"week":12,"game_type":"REG","date":"2015-11-29","team":"DEN","opp":"NE","home":true,"stats":{"tackles_solo":2,"tackles":2}},{"season":2015,"week":14,"game_type":"REG","date":"2015-12-13","team":"DEN","opp":"LV","home":true,"stats":{"tackles_solo":2,"tackles":2,"pass_defended":1}},{"season":2015,"week":15,"game_type":"REG","date":"2015-12-20","team":"DEN","opp":"PIT","home":false,"stats":{"tackles_solo":4,"tackles":4}},{"season":2015,"week":16,"game_type":"REG","date":"2015-12-28","team":"DEN","opp":"CIN","home":true,"stats":{"tackles_solo":4,"tackles":4,"tfl":1,"pass_defended":1}},{"season":2015,"week":17,"game_type":"REG","date":"2016-01-03","team":"DEN","opp":"LAC","home":true,"stats":{"tackles_solo":2,"tackles":2,"pass_defended":2}},{"season":2015,"week":19,"game_type":"DIV","date":"2016-01-17","team":"DEN","opp":"PIT","home":true,"stats":{"tackles_solo":3,"tackles":3,"ff":1}},{"season":2015,"week":21,"game_type":"SB","date":"2016-02-07","team":"DEN","opp":"CAR","home":true,"stats":{"tackles_solo":2,"tackles":2,"pass_defended":3}},{"season":2016,"week":1,"game_type":"REG","date":"2016-09-08","team":"DEN","opp":"CAR","home":true,"stats":{"tackles_solo":5,"tackles":5}},{"season":2016,"week":3,"game_type":"REG","date":"2016-09-25","team":"DEN","opp":"CIN","home":false,"stats":{"tackles_solo":2,"tackles":2}},{"season":2016,"week":4,"game_type":"REG","date":"2016-10-02","team":"DEN","opp":"TB","home":false,"stats":{"tackles_solo":2,"tackles":2}},{"season":2016,"week":5,"game_type":"REG","date":"2016-10-09","team":"DEN","opp":"ATL","home":true,"stats":{"tackles_solo":2,"tackles":2}},{"season":2016,"week":6,"game_type":"REG","date":"2016-10-13","team":"DEN","opp":"LAC","home":false,"stats":{"tackles_solo":1,"tackles":1,"pass_defended":2}},{"season":2016,"week":7,"game_type":"REG","date":"2016-10-24","team":"DEN","opp":"HOU","home":true,"stats":{"tackles_solo":1,"tackles":1}},{"season":2016,"week":8,"game_type":"REG","date":"2016-10-30","team":"DEN","opp":"LAC","home":true,"stats":{"tackles_solo":4,"tackles":7,"def_int":1,"pass_defended":2,"def_td":1}},{"season":2016,"week":9,"game_type":"REG","date":"2016-11-06","team":"DEN","opp":"LV","home":false,"stats":{"tackles_solo":7,"tackles":8,"def_sacks":1.0}},{"season":2016,"week":10,"game_type":"REG","date":"2016-11-13","team":"DEN","opp":"NO","home":false,"stats":{"tackles_solo":2,"tackles":2,"pass_defended":2,"ff":1}},{"season":2016,"week":12,"game_type":"REG","date":"2016-11-27","team":"DEN","opp":"KC","home":true,"stats":{"tackles_solo":1,"tackles":2}},{"season":2016,"week":13,"game_type":"REG","date":"2016-12-04","team":"DEN","opp":"JAX","home":false,"stats":{"tackles_solo":3,"tackles":3,"def_int":1,"pass_defended":2,"def_td":1}},{"season":2016,"week":17,"game_type":"REG","date":"2017-01-01","team":"DEN","opp":"LV","home":true,"stats":{"tackles_solo":3,"tackles":3}},{"season":2017,"week":1,"game_type":"REG","date":"2017-09-11","team":"DEN","opp":"LAC","home":true,"stats":{"tackles_solo":3,"tackles":5,"def_int":1,"pass_defended":2}},{"season":2017,"week":2,"game_type":"REG","date":"2017-09-17","team":"DEN","opp":"DAL","home":true,"stats":{"tackles_solo":2,"tackles":2,"pass_defended":1}},{"season":2017,"week":3,"game_type":"REG","date":"2017-09-24","team":"DEN","opp":"BUF","home":false,"stats":{"tackles_solo":3,"tackles":4,"pass_defended":1}},{"season":2017,"week":4,"game_type":"REG","date":"2017-10-01","team":"DEN","opp":"LV","home":true,"stats":{"tackles_solo":2,"tackles":2,"pass_defended":1}},{"season":2017,"week":6,"game_type":"REG","date":"2017-10-15","team":"DEN","opp":"NYG","home":true,"stats":{"tackles_solo":2,"tackles":2,"pass_defended":1}},{"season":2017,"week":7,"game_type":"REG","date":"2017-10-22","team":"DEN","opp":"LAC","home":false,"stats":{"tackles_solo":3,"tackles":3,"pass_defended":2}},{"season":2017,"week":8,"game_type":"REG","date":"2017-10-30","team":"DEN","opp":"KC","home":false,"stats":{"tackles_solo":2,"tackles":2}},{"season":2017,"week":9,"game_type":"REG","date":"2017-11-05","team":"DEN","opp":"PHI","home":false,"stats":{"tackles_solo":5,"tackles":5,"pass_defended":1}},{"season":2017,"week":10,"game_type":"REG","date":"2017-11-12","team":"DEN","opp":"NE","home":true,"stats":{"tackles_solo":2,"tackles":2,"tfl":1,"pass_defended":1}},{"season":2017,"week":11,"game_type":"REG","date":"2017-11-19","team":"DEN","opp":"CIN","home":true,"stats":{"tackles":1,"pass_defended":1}},{"season":2017,"week":12,"game_type":"REG","date":"2017-11-26","team":"DEN","opp":"LV","home":false,"stats":{"tackles_solo":3,"tackles":3,"pass_defended":1}},{"season":2017,"week":13,"game_type":"REG","date":"2017-12-03","team":"DEN","opp":"MIA","home":false,"stats":{"tackles_solo":3,"tackles":4,"pass_defended":3,"ff":1,"fr":1}},{"season":2017,"week":14,"game_type":"REG","date":"2017-12-10","team":"DEN","opp":"NYJ","home":true,"stats":{"tackles_solo":1,"tackles":1,"pass_defended":1}},{"season":2017,"week":15,"game_type":"REG","date":"2017-12-14","team":"DEN","opp":"IND","home":false,"stats":{"tackles_solo":1,"tackles":1,"def_sacks":1.0,"qb_hits":1}},{"season":2017,"week":16,"game_type":"REG","date":"2017-12-24","team":"DEN","opp":"WAS","home":false,"stats":{"tackles_solo":2,"tackles":3,"pass_defended":1}},{"season":2017,"week":17,"game_type":"REG","date":"2017-12-31","team":"DEN","opp":"KC","home":true,"stats":{"tackles_solo":1,"tackles":2}},{"season":2018,"week":1,"game_type":"REG","date":"2018-09-09","team":"DEN","opp":"SEA","home":true,"stats":{"tackles_solo":2,"tackles":2}},{"season":2018,"week":2,"game_type":"REG","date":"2018-09-16","team":"DEN","opp":"LV","home":true,"stats":{"tackles_solo":5,"tackles":5}},{"season":2018,"week":3,"game_type":"REG","date":"2018-09-23","team":"DEN","opp":"BAL","home":false,"stats":{"tackles_solo":2,"tackles":2}},{"season":2018,"week":4,"game_type":"REG","date":"2018-10-01","team":"DEN","opp":"KC","home":true,"stats":{"tackles_solo":3,"tackles":3,"pass_defended":1}},{"season":2018,"week":5,"game_type":"REG","date":"2018-10-07","team":"DEN","opp":"NYJ","home":false,"stats":{"pass_defended":1}},{"season":2018,"week":6,"game_type":"REG","date":"2018-10-14","team":"DEN","opp":"LA","home":true,"stats":{"tackles_solo":1,"tackles":1,"tfl":1,"pass_defended":1}},{"season":2018,"week":7,"game_type":"REG","date":"2018-10-18","team":"DEN","opp":"ARI","home":false,"stats":{"tackles_solo":2,"tackles":2,"def_int":1,"pass_defended":4}},{"season":2018,"week":8,"game_type":"REG","date":"2018-10-28","team":"DEN","opp":"KC","home":false,"stats":{"tackles_solo":5,"tackles":6}},{"season":2018,"week":11,"game_type":"REG","date":"2018-11-18","team":"DEN","opp":"LAC","home":false,"stats":{"tackles_solo":2,"tackles":3,"pass_defended":2}},{"season":2018,"week":12,"game_type":"REG","date":"2018-11-25","team":"DEN","opp":"PIT","home":true,"stats":{"tackles_solo":6,"tackles":6,"pass_defended":1,"ff":1}},{"season":2018,"week":13,"game_type":"REG","date":"2018-12-02","team":"DEN","opp":"CIN","home":false,"stats":{"tackles_solo":1,"tackles":3,"pass_defended":1}},{"season":2018,"week":14,"game_type":"REG","date":"2018-12-09","team":"DEN","opp":"SF","home":false,"stats":{"tackles_solo":3,"tackles":3,"ff":1}},{"season":2018,"week":15,"game_type":"REG","date":"2018-12-15","team":"DEN","opp":"CLE","home":true,"stats":{"tackles_solo":3,"tackles":4,"pass_defended":1}},{"season":2018,"week":16,"game_type":"REG","date":"2018-12-24","team":"DEN","opp":"LV","home":false,"stats":{"tackles_solo":3,"tackles":3}},{"season":2018,"week":17,"game_type":"REG","date":"2018-12-30","team":"DEN","opp":"LAC","home":true,"stats":{"tackles_solo":5,"tackles":5}},{"season":2019,"week":1,"game_type":"REG","date":"2019-09-09","team":"HOU","opp":"NO","home":false,"stats":{"tackles_solo":8,"tackles":9}},{"season":2019,"week":2,"game_type":"REG","date":"2019-09-15","team":"HOU","opp":"JAX","home":true,"stats":{"tackles_solo":2,"tackles":2}},{"season":2019,"week":3,"game_type":"REG","date":"2019-09-22","team":"HOU","opp":"LAC","home":false,"stats":{"tackles_solo":3,"tackles":3,"tfl":1}},{"season":2019,"week":4,"game_type":"REG","date":"2019-09-29","team":"HOU","opp":"CAR","home":true,"stats":{"tackles_solo":2,"tackles":2,"pass_defended":1}},{"season":2019,"week":5,"game_type":"REG","date":"2019-10-06","team":"HOU","opp":"ATL","home":true,"stats":{"tackles_solo":6,"tackles":7,"pass_defended":1,"ff":1}},{"season":2019,"week":6,"game_type":"REG","date":"2019-10-13","team":"HOU","opp":"KC","home":false,"stats":{"tackles_solo":1,"tackles":1,"pass_defended":2}},{"season":2019,"week":13,"game_type":"REG","date":"2019-12-01","team":"HOU","opp":"NE","home":true,"stats":{"tackles_solo":3,"tackles":4,"tfl":1,"def_sacks":1.0,"qb_hits":1,"def_int":1,"pass_defended":1}},{"season":2019,"week":14,"game_type":"REG","date":"2019-12-08","team":"HOU","opp":"DEN","home":true,"stats":{"tackles_solo":2,"tackles":2}},{"season":2019,"week":15,"game_type":"REG","date":"2019-12-15","team":"HOU","opp":"TEN","home":false,"stats":{"tackles_solo":3,"tackles":3,"pass_defended":1}},{"season":2019,"week":16,"game_type":"REG","date":"2019-12-21","team":"HOU","opp":"TB","home":false,"stats":{"tackles_solo":4,"tackles":4,"def_int":1,"pass_defended":2,"def_td":1}},{"season":2019,"week":18,"game_type":"WC","date":"2020-01-04","team":"HOU","opp":"BUF","home":true,"stats":{"tackles_solo":7,"tackles":7,"pass_defended":2}},{"season":2019,"week":19,"game_type":"DIV","date":"2020-01-12","team":"HOU","opp":"KC","home":false,"stats":{"tackles_solo":4,"tackles":4}},{"season":2020,"week":1,"game_type":"REG","date":"2020-09-10","team":"HOU","opp":"KC","home":false,"stats":{"tackles_solo":6,"tackles":6,"tfl":1}},{"season":2020,"week":2,"game_type":"REG","date":"2020-09-20","team":"HOU","opp":"BAL","home":true,"stats":{"tackles_solo":2,"tackles":2}},{"season":2020,"week":3,"game_type":"REG","date":"2020-09-27","team":"HOU","opp":"PIT","home":false,"stats":{"tackles_solo":2,"tackles":2,"pass_defended":1}},{"season":2020,"week":4,"game_type":"REG","date":"2020-10-04","team":"HOU","opp":"MIN","home":true,"stats":{"tackles_solo":6,"tackles":7,"pass_defended":2}},{"season":2020,"week":5,"game_type":"REG","date":"2020-10-11","team":"HOU","opp":"JAX","home":true,"stats":{"tackles_solo":4,"tackles":5}},{"season":2020,"week":6,"game_type":"REG","date":"2020-10-18","team":"HOU","opp":"TEN","home":false,"stats":{"tackles_solo":5,"tackles":6,"def_int":1,"pass_defended":2}},{"season":2020,"week":10,"game_type":"REG","date":"2020-11-15","team":"HOU","opp":"CLE","home":false,"stats":{"tackles_solo":3,"tackles":3}},{"season":2020,"week":11,"game_type":"REG","date":"2020-11-22","team":"HOU","opp":"NE","home":true,"stats":{"tackles_solo":3,"tackles":4,"tfl":1,"pass_defended":1}},{"season":2020,"week":12,"game_type":"REG","date":"2020-11-26","team":"HOU","opp":"DET","home":false,"stats":{"pass_defended":1,"fr":1}},{"season":2021,"week":2,"game_type":"REG","date":"2021-09-19","team":"NO","opp":"CAR","home":false,"stats":{"tackles_solo":1,"tackles":2,"tfl":1,"def_sacks":1.0,"qb_hits":1}},{"season":2021,"week":4,"game_type":"REG","date":"2021-10-03","team":"NO","opp":"NYG","home":true,"stats":{"tackles_solo":1,"tackles":1}},{"season":2021,"week":7,"game_type":"REG","date":"2021-10-25","team":"NO","opp":"SEA","home":false,"stats":{"tackles_solo":1,"tackles":2,"tfl":1}},{"season":2021,"week":8,"game_type":"REG","date":"2021-10-31","team":"NO","opp":"TB","home":true,"stats":{"tackles_solo":2,"tackles":2}},{"season":2021,"week":10,"game_type":"REG","date":"2021-11-14","team":"NO","opp":"TEN","home":false,"stats":{"tackles":1,"qb_hits":1,"pass_defended":1}},{"season":2021,"week":11,"game_type":"REG","date":"2021-11-21","team":"NO","opp":"PHI","home":false,"stats":{"tackles_solo":2,"tackles":2,"tfl":1,"qb_hits":1}},{"season":2021,"week":12,"game_type":"REG","date":"2021-11-25","team":"NO","opp":"BUF","home":true,"stats":{"tackles_solo":7,"tackles":8,"def_int":1,"pass_defended":1}},{"season":2021,"week":13,"game_type":"REG","date":"2021-12-02","team":"NO","opp":"DAL","home":true,"stats":{"tackles_solo":1,"tackles":1,"pass_defended":2}},{"season":2021,"week":14,"game_type":"REG","date":"2021-12-12","team":"NO","opp":"NYJ","home":false,"stats":{"tackles_solo":1,"tackles":1}},{"season":2021,"week":15,"game_type":"REG","date":"2021-12-19","team":"NO","opp":"TB","home":false,"stats":{"tackles_solo":2,"tackles":2}},{"season":2021,"week":16,"game_type":"REG","date":"2021-12-27","team":"NO","opp":"MIA","home":true,"stats":{"tackles_solo":1,"tackles":1,"pass_defended":1}},{"season":2022,"week":1,"game_type":"REG","date":"2022-09-11","team":"NO","opp":"ATL","home":false,"stats":{"tackles_solo":5,"tackles":5,"pass_defended":1,"fr":1}},{"season":2022,"week":2,"game_type":"REG","date":"2022-09-18","team":"NO","opp":"TB","home":true,"stats":{"tackles_solo":4,"tackles":5}},{"season":2022,"week":3,"game_type":"REG","date":"2022-09-25","team":"NO","opp":"CAR","home":false,"stats":{"tackles_solo":3,"tackles":4,"pass_defended":1}},{"season":2022,"week":4,"game_type":"REG","date":"2022-10-02","team":"NO","opp":"MIN","home":true,"stats":{"tackles_solo":1,"tackles":2,"tfl":1}},{"season":2022,"week":5,"game_type":"REG","date":"2022-10-09","team":"NO","opp":"SEA","home":true,"stats":{"tackles_solo":1,"tackles":1}},{"season":2022,"week":6,"game_type":"REG","date":"2022-10-16","team":"NO","opp":"CIN","home":true,"stats":{"tackles_solo":1,"tackles":2}},{"season":2022,"week":7,"game_type":"REG","date":"2022-10-20","team":"NO","opp":"ARI","home":false,"stats":{"tackles_solo":1,"tackles":1}},{"season":2022,"week":12,"game_type":"REG","date":"2022-11-27","team":"NO","opp":"SF","home":false,"stats":{"tackles_solo":1,"tackles":2}},{"season":2022,"week":13,"game_type":"REG","date":"2022-12-05","team":"NO","opp":"TB","home":false,"stats":{"tackles_solo":6,"tackles":8,"pass_defended":1}},{"season":2022,"week":15,"game_type":"REG","date":"2022-12-18","team":"NO","opp":"ATL","home":true,"stats":{"tackles_solo":1,"tackles":1,"fr":1}},{"season":2022,"week":16,"game_type":"REG","date":"2022-12-24","team":"NO","opp":"CLE","home":false,"stats":{"tackles_solo":3,"tackles":3,"pass_defended":1}},{"season":2022,"week":17,"game_type":"REG","date":"2023-01-01","team":"NO","opp":"PHI","home":false,"stats":{"tackles_solo":1,"tackles":1}},{"season":2022,"week":18,"game_type":"REG","date":"2023-01-08","team":"NO","opp":"CAR","home":true,"stats":{"pass_defended":1}},{"season":2023,"week":5,"game_type":"REG","date":"2023-10-08","team":"PHI","opp":"LA","home":false,"stats":{"tackles_solo":1,"tackles":1}},{"season":2023,"week":6,"game_type":"REG","date":"2023-10-15","team":"PHI","opp":"NYJ","home":false,"stats":{"tackles_solo":1,"tackles":1}},{"season":2023,"week":11,"game_type":"REG","date":"2023-11-20","team":"PHI","opp":"KC","home":false,"stats":{"tackles_solo":5,"tackles":5,"ff":1}},{"season":2023,"week":12,"game_type":"REG","date":"2023-11-26","team":"PHI","opp":"BUF","home":true,"stats":{"tackles_solo":3,"tackles":3,"qb_hits":1}},{"season":2023,"week":13,"game_type":"REG","date":"2023-12-03","team":"PHI","opp":"SF","home":true,"stats":{"tackles_solo":1,"tackles":2}},{"season":2023,"week":14,"game_type":"REG","date":"2023-12-10","team":"PHI","opp":"DAL","home":false,"stats":{"tackles_solo":4,"tackles":6,"tfl":1}},{"season":2023,"week":15,"game_type":"REG","date":"2023-12-18","team":"PHI","opp":"SEA","home":false,"stats":{"tackles_solo":2,"tackles":2,"tfl":1}},{"season":2023,"week":18,"game_type":"REG","date":"2024-01-07","team":"PHI","opp":"NYG","home":false,"stats":{"tackles_solo":1,"tackles":1}},{"season":2023,"week":19,"game_type":"WC","date":"2024-01-15","team":"PHI","opp":"TB","home":false,"stats":{"tackles_solo":2,"tackles":3}}]}
