{"schema_version":1,"id":"00-0037265","profile":{"name":"Snoop Conner","pos":"RB","dob":"2000-08-01","height_in":70,"weight_lb":222,"college":"Mississippi","draft":{"year":2022,"round":5,"pick":154,"team":"JAX"},"headshot":"https://static.www.nfl.com/image/upload/f_auto,q_auto/league/hkoa2nrn7xnco6kibhpg","teams":["JAX"]},"seasons":[{"season":2022,"team":"JAX","teams":["JAX"],"pos":"RB","games":5,"game_type":"REG","stats":{"rush_att":12,"rush_yds":42,"rush_td":1,"tackles_solo":1,"tackles":1},"advanced":{"epa_per_play":-0.171,"ngs":null},"percentiles":{}}],"career":{"games":5,"stats":{"rush_att":12,"rush_yds":42,"rush_td":1,"tackles_solo":1,"tackles":1},"advanced":{"epa_per_play":-0.171,"n_plays":12}},"game_logs":[{"season":2022,"week":12,"game_type":"REG","date":"2022-11-27","team":"JAX","opp":"BAL","home":true,"stats":{"rush_att":3,"rush_yds":11}},{"season":2022,"week":13,"game_type":"REG","date":"2022-12-04","team":"JAX","opp":"DET","home":false,"stats":{"rush_att":1,"rush_yds":6}},{"season":2022,"week":15,"game_type":"REG","date":"2022-12-18","team":"JAX","opp":"DAL","home":true,"stats":{"rush_att":1,"rush_yds":3,"tackles_solo":1,"tackles":1}},{"season":2022,"week":16,"game_type":"REG","date":"2022-12-22","team":"JAX","opp":"NYJ","home":false,"stats":{"rush_att":2,"rush_yds":5}},{"season":2022,"week":17,"game_type":"REG","date":"2023-01-01","team":"JAX","opp":"HOU","home":false,"stats":{"rush_att":5,"rush_yds":17,"rush_td":1}}]}
