{"schema_version":1,"id":"00-0028278","profile":{"name":"Josh Bynes","pos":"ILB","dob":"1989-08-24","height_in":73,"weight_lb":235,"college":"Auburn","draft":null,"headshot":"https://static.www.nfl.com/image/private/f_auto,q_auto/league/yki1iqv1tu8hvta68ypu","teams":["DET","ARI","BAL","CIN"]},"seasons":[{"season":2015,"team":"DET","teams":["DET"],"pos":"OLB","games":16,"game_type":"REG","stats":{"tackles_solo":53,"tackles":79,"tfl":5,"def_sacks":0.5,"qb_hits":3,"pass_defended":5,"ff":1},"percentiles":{}},{"season":2016,"team":"DET","teams":["DET"],"pos":"LB","games":8,"game_type":"REG","stats":{"tackles_solo":24,"tackles":36,"tfl":4,"pass_defended":4},"percentiles":{}},{"season":2016,"team":"DET","teams":["DET"],"pos":"LB","games":1,"game_type":"POST","stats":{"tackles_solo":1,"tackles":7},"percentiles":{}},{"season":2017,"team":"ARI","teams":["ARI"],"pos":"LB","games":11,"game_type":"REG","stats":{"tackles_solo":28,"tackles":33,"tfl":2,"def_sacks":1.0,"qb_hits":1,"def_int":1,"pass_defended":3,"ff":2},"percentiles":{}},{"season":2018,"team":"ARI","teams":["ARI"],"pos":"LB","games":11,"game_type":"REG","stats":{"tackles_solo":45,"tackles":68,"tfl":5,"def_sacks":2.0,"qb_hits":3,"pass_defended":5,"fr":1,"def_td":1},"percentiles":{}},{"season":2019,"team":"BAL","teams":["BAL"],"pos":"LB","games":12,"game_type":"REG","stats":{"tackles_solo":21,"tackles":44,"tfl":6,"def_sacks":1.0,"qb_hits":2,"def_int":2,"pass_defended":4},"percentiles":{}},{"season":2019,"team":"BAL","teams":["BAL"],"pos":"LB","games":1,"game_type":"POST","stats":{"tackles_solo":2,"tackles":6},"percentiles":{}},{"season":2020,"team":"CIN","teams":["CIN"],"pos":"LB","games":16,"game_type":"REG","stats":{"tackles_solo":48,"tackles":94,"tfl":5,"def_sacks":1.0,"qb_hits":2,"pass_defended":2,"fr":1},"percentiles":{}},{"season":2021,"team":"BAL","teams":["BAL"],"pos":"LB","games":13,"game_type":"REG","stats":{"tackles_solo":38,"tackles":64,"tfl":6,"def_sacks":2.0,"qb_hits":3,"pass_defended":4},"percentiles":{}},{"season":2022,"team":"BAL","teams":["BAL"],"pos":"LB","games":7,"game_type":"REG","stats":{"tackles_solo":16,"tackles":26,"tfl":2,"def_sacks":1.0,"qb_hits":1,"def_int":1,"pass_defended":2},"percentiles":{}}],"career":{"games":94,"stats":{"tackles_solo":273,"tackles":444,"tfl":35,"def_sacks":8.5,"qb_hits":15,"pass_defended":29,"ff":3,"def_int":4,"fr":2,"def_td":1}},"career_post":{"games":2,"stats":{"tackles_solo":3,"tackles":13}},"game_logs":[{"season":2015,"week":1,"game_type":"REG","date":"2015-09-13","team":"DET","opp":"LAC","home":false,"stats":{"tackles_solo":5,"tackles":7}},{"season":2015,"week":2,"game_type":"REG","date":"2015-09-20","team":"DET","opp":"MIN","home":false,"stats":{"tackles_solo":3,"tackles":4,"tfl":1}},{"season":2015,"week":3,"game_type":"REG","date":"2015-09-27","team":"DET","opp":"DEN","home":true,"stats":{"tackles_solo":3,"tackles":7,"pass_defended":1}},{"season":2015,"week":4,"game_type":"REG","date":"2015-10-05","team":"DET","opp":"SEA","home":false,"stats":{"tackles_solo":2,"tackles":5,"tfl":1}},{"season":2015,"week":5,"game_type":"REG","date":"2015-10-11","team":"DET","opp":"ARI","home":true,"stats":{"tackles":3,"qb_hits":1}},{"season":2015,"week":6,"game_type":"REG","date":"2015-10-18","team":"DET","opp":"CHI","home":true,"stats":{"tackles_solo":9,"tackles":11,"tfl":2,"pass_defended":1}},{"season":2015,"week":7,"game_type":"REG","date":"2015-10-25","team":"DET","opp":"MIN","home":true,"stats":{"tackles_solo":4,"tackles":7}},{"season":2015,"week":8,"game_type":"REG","date":"2015-11-01","team":"DET","opp":"KC","home":false,"stats":{"tackles_solo":3,"tackles":4}},{"season":2015,"week":10,"game_type":"REG","date":"2015-11-15","team":"DET","opp":"GB","home":false,"stats":{"tackles_solo":2,"tackles":2}},{"season":2015,"week":11,"game_type":"REG","date":"2015-11-22","team":"DET","opp":"LV","home":true,"stats":{"tackles_solo":2,"tackles":3,"pass_defended":1}},{"season":2015,"week":12,"game_type":"REG","date":"2015-11-26","team":"DET","opp":"PHI","home":true,"stats":{"tackles_solo":2,"tackles":2}},{"season":2015,"week":13,"game_type":"REG","date":"2015-12-03","team":"DET","opp":"GB","home":true,"stats":{"tackles_solo":3,"tackles":4,"qb_hits":1}},{"season":2015,"week":14,"game_type":"REG","date":"2015-12-13","team":"DET","opp":"LA","home":false,"stats":{"tackles_solo":7,"tackles":8,"tfl":1}},{"season":2015,"week":15,"game_type":"REG","date":"2015-12-21","team":"DET","opp":"NO","home":false,"stats":{"tackles_solo":3,"tackles":5,"qb_hits":1,"pass_defended":2}},{"season":2015,"week":16,"game_type":"REG","date":"2015-12-27","team":"DET","opp":"SF","home":true,"stats":{"tackles_solo":3,"tackles":5,"def_sacks":0.5,"ff":1}},{"season":2015,"week":17,"game_type":"REG","date":"2016-01-03","team":"DET","opp":"CHI","home":false,"stats":{"tackles_solo":2,"tackles":2}},{"season":2016,"week":8,"game_type":"REG","date":"2016-10-30","team":"DET","opp":"HOU","home":false,"stats":{"tackles_solo":2,"tackles":2}},{"season":2016,"week":9,"game_type":"REG","date":"2016-11-06","team":"DET","opp":"MIN","home":false,"stats":{"tackles_solo":5,"tackles":6}},{"season":2016,"week":12,"game_type":"REG","date":"2016-11-24","team":"DET","opp":"MIN","home":true,"stats":{"tackles_solo":3,"tackles":4,"tfl":1,"pass_defended":1}},{"season":2016,"week":13,"game_type":"REG","date":"2016-12-04","team":"DET","opp":"NO","home":false,"stats":{"tackles_solo":5,"tackles":8,"tfl":1,"pass_defended":1}},{"season":2016,"week":14,"game_type":"REG","date":"2016-12-11","team":"DET","opp":"CHI","home":true,"stats":{"tackles_solo":5,"tackles":6,"tfl":2,"pass_defended":1}},{"season":2016,"week":15,"game_type":"REG","date":"2016-12-18","team":"DET","opp":"NYG","home":false,"stats":{"tackles_solo":1,"tackles":5}},{"season":2016,"week":16,"game_type":"REG","date":"2016-12-26","team":"DET","opp":"DAL","home":false,"stats":{"tackles_solo":2,"tackles":3}},{"season":2016,"week":17,"game_type":"REG","date":"2017-01-01","team":"DET","opp":"GB","home":true,"stats":{"tackles_solo":1,"tackles":2,"pass_defended":1}},{"season":2016,"week":18,"game_type":"WC","date":"2017-01-07","team":"DET","opp":"SEA","home":false,"stats":{"tackles_solo":1,"tackles":7}},{"season":2017,"week":1,"game_type":"REG","date":"2017-09-10","team":"ARI","opp":"DET","home":false,"stats":{"tackles_solo":4,"tackles":4}},{"season":2017,"week":2,"game_type":"REG","date":"2017-09-17","team":"ARI","opp":"IND","home":false,"stats":{"tackles_solo":4,"tackles":4,"tfl":1,"def_sacks":1.0,"qb_hits":1,"ff":1}},{"season":2017,"week":3,"game_type":"REG","date":"2017-09-25","team":"ARI","opp":"DAL","home":true,"stats":{"tackles_solo":1,"tackles":1}},{"season":2017,"week":4,"game_type":"REG","date":"2017-10-01","team":"ARI","opp":"SF","home":true,"stats":{"tackles_solo":2,"tackles":2}},{"season":2017,"week":5,"game_type":"REG","date":"2017-10-08","team":"ARI","opp":"PHI","home":false,"stats":{"tackles":1}},{"season":2017,"week":7,"game_type":"REG","date":"2017-10-22","team":"ARI","opp":"LA","home":false,"stats":{"tackles_solo":1,"tackles":2,"pass_defended":1}},{"season":2017,"week":10,"game_type":"REG","date":"2017-11-09","team":"ARI","opp":"SEA","home":true,"stats":{"tackles_solo":1,"tackles":1}},{"season":2017,"week":12,"game_type":"REG","date":"2017-11-26","team":"ARI","opp":"JAX","home":true,"stats":{"tackles_solo":7,"tackles":8,"ff":1}},{"season":2017,"week":13,"game_type":"REG","date":"2017-12-03","team":"ARI","opp":"LA","home":true,"stats":{"tackles_solo":8,"tackles":8,"tfl":1,"pass_defended":1}},{"season":2017,"week":14,"game_type":"REG","date":"2017-12-10","team":"ARI","opp":"TEN","home":true,"stats":{"def_int":1,"pass_defended":1}},{"season":2017,"week":15,"game_type":"REG","date":"2017-12-17","team":"ARI","opp":"WAS","home":false,"stats":{"tackles":2}},{"season":2018,"week":1,"game_type":"REG","date":"2018-09-09","team":"ARI","opp":"WAS","home":true,"stats":{"tackles_solo":8,"tackles":11}},{"season":2018,"week":2,"game_type":"REG","date":"2018-09-16","team":"ARI","opp":"LA","home":false,"stats":{"tackles_solo":2,"tackles":4,"pass_defended":1}},{"season":2018,"week":3,"game_type":"REG","date":"2018-09-23","team":"ARI","opp":"CHI","home":true,"stats":{"tackles_solo":7,"tackles":10}},{"season":2018,"week":4,"game_type":"REG","date":"2018-09-30","team":"ARI","opp":"SEA","home":true,"stats":{"tackles_solo":4,"tackles":4}},{"season":2018,"week":5,"game_type":"REG","date":"2018-10-07","team":"ARI","opp":"SF","home":false,"stats":{"tackles_solo":6,"tackles":8,"tfl":1,"def_sacks":1.0,"qb_hits":1,"pass_defended":1,"fr":1,"def_td":1}},{"season":2018,"week":6,"game_type":"REG","date":"2018-10-14","team":"ARI","opp":"MIN","home":false,"stats":{"tackles_solo":3,"tackles":7,"tfl":1}},{"season":2018,"week":7,"game_type":"REG","date":"2018-10-18","team":"ARI","opp":"DEN","home":true,"stats":{"tackles_solo":2,"tackles":5}},{"season":2018,"week":8,"game_type":"REG","date":"2018-10-28","team":"ARI","opp":"SF","home":true,"stats":{"tackles_solo":4,"tackles":5,"tfl":1,"qb_hits":1,"pass_defended":1}},{"season":2018,"week":10,"game_type":"REG","date":"2018-11-11","team":"ARI","opp":"KC","home":false,"stats":{"tackles_solo":2,"tackles":3,"tfl":1,"def_sacks":1.0,"qb_hits":1,"pass_defended":1}},{"season":2018,"week":11,"game_type":"REG","date":"2018-11-18","team":"ARI","opp":"LV","home":true,"stats":{"tackles_solo":6,"tackles":8,"tfl":1,"pass_defended":1}},{"season":2018,"week":12,"game_type":"REG","date":"2018-11-25","team":"ARI","opp":"LAC","home":false,"stats":{"tackles_solo":1,"tackles":3}},{"season":2019,"week":5,"game_type":"REG","date":"2019-10-06","team":"BAL","opp":"PIT","home":false,"stats":{"tackles_solo":2,"tackles":4,"def_int":1,"pass_defended":1}},{"season":2019,"week":6,"game_type":"REG","date":"2019-10-13","team":"BAL","opp":"CIN","home":true,"stats":{"tackles_solo":2,"tackles":3,"tfl":1,"pass_defended":1}},{"season":2019,"week":7,"game_type":"REG","date":"2019-10-20","team":"BAL","opp":"SEA","home":false,"stats":{"tackles_solo":2,"tackles":7,"tfl":1}},{"season":2019,"week":9,"game_type":"REG","date":"2019-11-03","team":"BAL","opp":"NE","home":true,"stats":{"tackles_solo":2,"tackles":2,"pass_defended":1}},{"season":2019,"week":10,"game_type":"REG","date":"2019-11-10","team":"BAL","opp":"CIN","home":false,"stats":{"tackles_solo":2,"tackles":9}},{"season":2019,"week":11,"game_type":"REG","date":"2019-11-17","team":"BAL","opp":"HOU","home":true,"stats":{"tackles_solo":1,"tackles":2,"def_int":1,"pass_defended":1}},{"season":2019,"week":12,"game_type":"REG","date":"2019-11-25","team":"BAL","opp":"LA","home":false,"stats":{"tackles_solo":1,"tackles":3,"tfl":1}},{"season":2019,"week":13,"game_type":"REG","date":"2019-12-01","team":"BAL","opp":"SF","home":true,"stats":{"tackles_solo":4,"tackles":5,"tfl":1}},{"season":2019,"week":14,"game_type":"REG","date":"2019-12-08","team":"BAL","opp":"BUF","home":false,"stats":{"tackles_solo":2,"tackles":2,"def_sacks":1.0,"qb_hits":2}},{"season":2019,"week":15,"game_type":"REG","date":"2019-12-12","team":"BAL","opp":"NYJ","home":true,"stats":{"tackles_solo":2,"tackles":4,"tfl":1}},{"season":2019,"week":16,"game_type":"REG","date":"2019-12-22","team":"BAL","opp":"CLE","home":false,"stats":{"tackles_solo":1,"tackles":1,"tfl":1}},{"season":2019,"week":17,"game_type":"REG","date":"2019-12-29","team":"BAL","opp":"PIT","home":true,"stats":{"tackles":2}},{"season":2019,"week":19,"game_type":"DIV","date":"2020-01-11","team":"BAL","opp":"TEN","home":true,"stats":{"tackles_solo":2,"tackles":6}},{"season":2020,"week":1,"game_type":"REG","date":"2020-09-13","team":"CIN","opp":"LAC","home":true,"stats":{"tackles_solo":3,"tackles":7,"tfl":1,"def_sacks":1.0,"qb_hits":1}},{"season":2020,"week":2,"game_type":"REG","date":"2020-09-17","team":"CIN","opp":"CLE","home":false,"stats":{"tackles_solo":2,"tackles":7}},{"season":2020,"week":3,"game_type":"REG","date":"2020-09-27","team":"CIN","opp":"PHI","home":false,"stats":{"tackles_solo":4,"tackles":7}},{"season":2020,"week":4,"game_type":"REG","date":"2020-10-04","team":"CIN","opp":"JAX","home":true,"stats":{"tackles_solo":1,"tackles":4}},{"season":2020,"week":5,"game_type":"REG","date":"2020-10-11","team":"CIN","opp":"BAL","home":false,"stats":{"tackles_solo":1,"tackles":7}},{"season":2020,"week":6,"game_type":"REG","date":"2020-10-18","team":"CIN","opp":"IND","home":false,"stats":{"tackles":1}},{"season":2020,"week":7,"game_type":"REG","date":"2020-10-25","team":"CIN","opp":"CLE","home":true,"stats":{"tackles_solo":4,"tackles":7,"tfl":1}},{"season":2020,"week":8,"game_type":"REG","date":"2020-11-01","team":"CIN","opp":"TEN","home":true,"stats":{"tackles_solo":2,"tackles":5}},{"season":2020,"week":10,"game_type":"REG","date":"2020-11-15","team":"CIN","opp":"PIT","home":false,"stats":{"tackles_solo":1,"tackles":2}},{"season":2020,"week":11,"game_type":"REG","date":"2020-11-22","team":"CIN","opp":"WAS","home":false,"stats":{"tackles_solo":3,"tackles":5}},{"season":2020,"week":12,"game_type":"REG","date":"2020-11-29","team":"CIN","opp":"NYG","home":true,"stats":{"tackles_solo":6,"tackles":7,"tfl":1,"qb_hits":1,"pass_defended":2}},{"season":2020,"week":13,"game_type":"REG","date":"2020-12-06","team":"CIN","opp":"MIA","home":false,"stats":{"tackles_solo":4,"tackles":6}},{"season":2020,"week":14,"game_type":"REG","date":"2020-12-13","team":"CIN","opp":"DAL","home":true,"stats":{"tackles_solo":4,"tackles":7,"tfl":1}},{"season":2020,"week":15,"game_type":"REG","date":"2020-12-21","team":"CIN","opp":"PIT","home":true,"stats":{"tackles_solo":3,"tackles":8,"tfl":1,"fr":1}},{"season":2020,"week":16,"game_type":"REG","date":"2020-12-27","team":"CIN","opp":"HOU","home":false,"stats":{"tackles_solo":3,"tackles":4}},{"season":2020,"week":17,"game_type":"REG","date":"2021-01-03","team":"CIN","opp":"BAL","home":true,"stats":{"tackles_solo":7,"tackles":10}},{"season":2021,"week":3,"game_type":"REG","date":"2021-09-26","team":"BAL","opp":"DET","home":false,"stats":{"tackles_solo":2,"tackles":4}},{"season":2021,"week":6,"game_type":"REG","date":"2021-10-17","team":"BAL","opp":"LAC","home":true,"stats":{"tackles_solo":2,"tackles":4,"tfl":2,"pass_defended":1}},{"season":2021,"week":7,"game_type":"REG","date":"2021-10-24","team":"BAL","opp":"CIN","home":true,"stats":{"tackles_solo":5,"tackles":6,"tfl":1}},{"season":2021,"week":9,"game_type":"REG","date":"2021-11-07","team":"BAL","opp":"MIN","home":true,"stats":{"tackles_solo":6,"tackles":9,"tfl":1,"pass_defended":1}},{"season":2021,"week":10,"game_type":"REG","date":"2021-11-11","team":"BAL","opp":"MIA","home":false,"stats":{"tackles_solo":3,"tackles":3,"tfl":1,"def_sacks":1.0,"qb_hits":2,"pass_defended":1}},{"season":2021,"week":11,"game_type":"REG","date":"2021-11-21","team":"BAL","opp":"CHI","home":false,"stats":{"tackles_solo":1,"tackles":1}},{"season":2021,"week":12,"game_type":"REG","date":"2021-11-28","team":"BAL","opp":"CLE","home":true,"stats":{"tackles_solo":2,"tackles":2,"tfl":1}},{"season":2021,"week":13,"game_type":"REG","date":"2021-12-05","team":"BAL","opp":"PIT","home":false,"stats":{"tackles_solo":1,"tackles":5}},{"season":2021,"week":14,"game_type":"REG","date":"2021-12-12","team":"BAL","opp":"CLE","home":false,"stats":{"tackles_solo":1,"tackles":5}},{"season":2021,"week":15,"game_type":"REG","date":"2021-12-19","team":"BAL","opp":"GB","home":true,"stats":{"tackles_solo":3,"tackles":6,"def_sacks":1.0,"qb_hits":1}},{"season":2021,"week":16,"game_type":"REG","date":"2021-12-26","team":"BAL","opp":"CIN","home":false,"stats":{"tackles_solo":4,"tackles":6,"pass_defended":1}},{"season":2021,"week":17,"game_type":"REG","date":"2022-01-02","team":"BAL","opp":"LA","home":true,"stats":{"tackles_solo":3,"tackles":6}},{"season":2021,"week":18,"game_type":"REG","date":"2022-01-09","team":"BAL","opp":"PIT","home":true,"stats":{"tackles_solo":5,"tackles":7}},{"season":2022,"week":1,"game_type":"REG","date":"2022-09-11","team":"BAL","opp":"NYJ","home":false,"stats":{"tackles_solo":1,"tackles":1}},{"season":2022,"week":2,"game_type":"REG","date":"2022-09-18","team":"BAL","opp":"MIA","home":true,"stats":{"tackles_solo":1,"tackles":1}},{"season":2022,"week":3,"game_type":"REG","date":"2022-09-25","team":"BAL","opp":"NE","home":false,"stats":{"tackles_solo":6,"tackles":8,"def_int":1,"pass_defended":1}},{"season":2022,"week":4,"game_type":"REG","date":"2022-10-02","team":"BAL","opp":"BUF","home":true,"stats":{"tackles_solo":2,"tackles":2,"pass_defended":1}},{"season":2022,"week":5,"game_type":"REG","date":"2022-10-09","team":"BAL","opp":"CIN","home":true,"stats":{"tackles_solo":4,"tackles":6,"tfl":1,"def_sacks":1.0,"qb_hits":1}},{"season":2022,"week":6,"game_type":"REG","date":"2022-10-16","team":"BAL","opp":"NYG","home":false,"stats":{"tackles_solo":2,"tackles":5,"tfl":1}},{"season":2022,"week":7,"game_type":"REG","date":"2022-10-23","team":"BAL","opp":"CLE","home":true,"stats":{"tackles":3}}]}
