{"schema_version":1,"id":"00-0025504","profile":{"name":"Manny Ramirez","pos":"G","dob":"1983-02-19","height_in":75,"weight_lb":325,"college":"Texas Tech","draft":{"year":2007,"round":4,"pick":117,"team":"DET"},"headshot":"https://static.www.nfl.com/image/private/f_auto,q_auto/league/jbltlppspwhvf4kctkqn","teams":["DET"]},"seasons":[{"season":2015,"team":"DET","teams":["DET"],"pos":"G","games":1,"game_type":"REG","stats":{"tackles_solo":1,"tackles":1},"percentiles":{}}],"career":{"games":1,"stats":{"tackles_solo":1,"tackles":1}},"game_logs":[{"season":2015,"week":5,"game_type":"REG","date":"2015-10-11","team":"DET","opp":"ARI","home":true,"stats":{"tackles_solo":1,"tackles":1}}]}
