{"schema_version":1,"id":"00-0036036","profile":{"name":"Terence Steele","pos":"OT","dob":"1997-06-04","height_in":78,"weight_lb":310,"college":"Texas Tech","draft":null,"headshot":"https://static.www.nfl.com/image/upload/f_auto,q_auto/league/ezmoh6joqsserp3ogcqc","teams":["DAL"]},"seasons":[{"season":2020,"team":"DAL","teams":["DAL"],"pos":"OL","games":1,"game_type":"REG","stats":{"tackles_solo":1,"tackles":1},"percentiles":{}},{"season":2021,"team":"DAL","teams":["DAL"],"pos":"OL","games":2,"game_type":"REG","stats":{"targets":1,"rec":1,"rec_yds":1,"rec_td":1,"rec_air_yds":1,"tackles_solo":1,"tackles":1,"target_share":0.001},"advanced":{"epa_per_play":1.191,"adot":1.0},"percentiles":{}},{"season":2022,"team":"DAL","teams":["DAL"],"pos":"OL","games":1,"game_type":"REG","stats":{"tackles_solo":1,"tackles":1},"percentiles":{}},{"season":2023,"team":"DAL","teams":["DAL"],"pos":"OL","games":1,"game_type":"REG","stats":{"tackles_solo":1,"tackles":1},"percentiles":{}},{"season":2025,"team":"DAL","teams":["DAL"],"pos":"OL","games":3,"game_type":"REG","stats":{},"percentiles":{}}],"career":{"games":8,"stats":{"tackles_solo":4,"tackles":4,"targets":1,"rec":1,"rec_yds":1,"rec_td":1,"rec_air_yds":1},"advanced":{"epa_per_play":1.191,"adot":1.0,"n_plays":1}},"game_logs":[{"season":2020,"week":2,"game_type":"REG","date":"2020-09-20","team":"DAL","opp":"ATL","home":true,"stats":{"tackles_solo":1,"tackles":1}},{"season":2021,"week":11,"game_type":"REG","date":"2021-11-21","team":"DAL","opp":"KC","home":false,"stats":{"tackles_solo":1,"tackles":1}},{"season":2021,"week":16,"game_type":"REG","date":"2021-12-26","team":"DAL","opp":"WAS","home":true,"stats":{"targets":1,"rec":1,"rec_yds":1,"rec_td":1,"rec_air_yds":1}},{"season":2022,"week":10,"game_type":"REG","date":"2022-11-13","team":"DAL","opp":"GB","home":false,"stats":{"tackles_solo":1,"tackles":1}},{"season":2023,"week":5,"game_type":"REG","date":"2023-10-08","team":"DAL","opp":"SF","home":false,"stats":{"tackles_solo":1,"tackles":1}}]}
