{"schema_version":1,"id":"00-0034342","profile":{"name":"Quenton Nelson","pos":"G","dob":"1996-03-19","height_in":77,"weight_lb":330,"college":"Notre Dame","draft":{"year":2018,"round":1,"pick":6,"team":"IND"},"headshot":"https://static.www.nfl.com/image/upload/f_auto,q_auto/league/wltd0vj7zlzbprlshf2d","teams":["IND"]},"seasons":[{"season":2018,"team":"IND","teams":["IND"],"pos":"OL","games":2,"game_type":"REG","stats":{"tackles_solo":2,"tackles":2},"percentiles":{}},{"season":2019,"team":"IND","teams":["IND"],"pos":"OL","games":1,"game_type":"REG","stats":{"rush_att":1},"advanced":{"epa_per_play":-0.964},"percentiles":{}},{"season":2020,"team":"IND","teams":["IND"],"pos":"OL","games":1,"game_type":"REG","stats":{"tackles_solo":1,"tackles":1},"percentiles":{}},{"season":2022,"team":"IND","teams":["IND"],"pos":"OL","games":1,"game_type":"REG","stats":{"tackles":1},"percentiles":{}},{"season":2023,"team":"IND","teams":["IND"],"pos":"OL","games":1,"game_type":"REG","stats":{"tackles_solo":1,"tackles":1},"percentiles":{}},{"season":2025,"team":"IND","teams":["IND"],"pos":"OL","games":2,"game_type":"REG","stats":{},"percentiles":{}}],"career":{"games":8,"stats":{"tackles_solo":4,"tackles":5,"rush_att":1},"advanced":{"epa_per_play":-0.964,"n_plays":1}},"game_logs":[{"season":2018,"week":5,"game_type":"REG","date":"2018-10-04","team":"IND","opp":"NE","home":false,"stats":{"tackles_solo":1,"tackles":1}},{"season":2018,"week":17,"game_type":"REG","date":"2018-12-30","team":"IND","opp":"TEN","home":false,"stats":{"tackles_solo":1,"tackles":1}},{"season":2019,"week":11,"game_type":"REG","date":"2019-11-17","team":"IND","opp":"JAX","home":true,"stats":{"rush_att":1}},{"season":2020,"week":5,"game_type":"REG","date":"2020-10-11","team":"IND","opp":"CLE","home":false,"stats":{"tackles_solo":1,"tackles":1}},{"season":2022,"week":18,"game_type":"REG","date":"2023-01-08","team":"IND","opp":"HOU","home":true,"stats":{"tackles":1}},{"season":2023,"week":6,"game_type":"REG","date":"2023-10-15","team":"IND","opp":"JAX","home":false,"stats":{"tackles_solo":1,"tackles":1}}]}
