{"schema_version":1,"id":"00-0037488","profile":{"name":"Nolan Turner","pos":"DB","dob":"1997-11-29","height_in":73,"weight_lb":202,"college":"Clemson","draft":null,"headshot":"https://static.www.nfl.com/image/private/f_auto,q_auto/league/zja76swfcjnoaysxdfyw","teams":["TB"]},"seasons":[{"season":2022,"team":"TB","teams":["TB"],"pos":"DB","games":1,"game_type":"REG","stats":{"tackles_solo":1,"tackles":1,"tfl":1},"percentiles":{}}],"career":{"games":1,"stats":{"tackles_solo":1,"tackles":1,"tfl":1}},"game_logs":[{"season":2022,"week":14,"game_type":"REG","date":"2022-12-11","team":"TB","opp":"SF","home":false,"stats":{"tackles_solo":1,"tackles":1,"tfl":1}}]}
