{"schema_version":1,"id":"00-0035758","profile":{"name":"Lirim Hajrullahu","pos":"K","dob":"1990-04-24","height_in":71,"weight_lb":205,"college":"Western Ontario","draft":null,"headshot":"https://static.www.nfl.com/image/private/f_auto,q_auto/league/nxgqgx0ue9xdo8mavn1u","teams":["CAR"]},"seasons":[{"season":2021,"team":"CAR","teams":["CAR"],"pos":"K","games":4,"game_type":"REG","stats":{"tackles_solo":1,"tackles":1,"fg_att":5,"fg_made":4,"fg_long":35,"xp_att":8,"xp_made":8},"percentiles":{}}],"career":{"games":4,"stats":{"tackles_solo":1,"tackles":1,"fg_att":5,"fg_made":4,"fg_long":35,"xp_att":8,"xp_made":8}},"game_logs":[{"season":2021,"week":10,"game_type":"REG","date":"2021-11-14","team":"ATL","opp":"DAL","home":false,"stats":{"xp_att":5,"xp_made":5}},{"season":2021,"week":16,"game_type":"REG","date":"2021-12-26","team":"CAR","opp":"TB","home":true,"stats":{"fg_att":2,"fg_made":2}},{"season":2021,"week":17,"game_type":"REG","date":"2022-01-02","team":"CAR","opp":"NO","home":false,"stats":{"fg_att":2,"fg_made":1,"xp_att":1,"xp_made":1}},{"season":2021,"week":18,"game_type":"REG","date":"2022-01-09","team":"CAR","opp":"TB","home":false,"stats":{"tackles_solo":1,"tackles":1,"fg_att":1,"fg_made":1,"xp_att":2,"xp_made":2}}]}
