{"schema_version":1,"id":"00-0036220","profile":{"name":"Derrick Brown","pos":"DT","dob":"1998-04-15","height_in":77,"weight_lb":320,"college":"Auburn","draft":{"year":2020,"round":1,"pick":7,"team":"CAR"},"headshot":"https://static.www.nfl.com/image/upload/f_auto,q_auto/league/xgaxvkpcxh41dyttf3sb","teams":["CAR"]},"seasons":[{"season":2020,"team":"CAR","teams":["CAR"],"pos":"DL","games":16,"game_type":"REG","stats":{"tackles_solo":20,"tackles":33,"tfl":8,"def_sacks":2.0,"qb_hits":12,"pass_defended":4,"snaps":742,"snap_share":0.706},"percentiles":{"tackles_solo":70.0,"tackles":58.9,"tfl":85.0,"def_sacks":41.7,"qb_hits":75.0,"pass_defended":90.0,"snaps":85.8,"snap_share":80.8}},{"season":2021,"team":"CAR","teams":["CAR"],"pos":"DL","games":16,"game_type":"REG","stats":{"tackles_solo":24,"tackles":38,"tfl":8,"def_sacks":3.0,"qb_hits":9,"pass_defended":4,"snaps":632,"snap_share":0.622},"percentiles":{"tackles_solo":86.2,"tackles":67.4,"tfl":85.0,"def_sacks":56.2,"qb_hits":60.0,"pass_defended":95.0,"snaps":71.0,"snap_share":70.2}},{"season":2022,"team":"CAR","teams":["CAR"],"pos":"DL","games":17,"game_type":"REG","stats":{"tackles_solo":24,"tackles":61,"tfl":5,"def_sacks":1.0,"qb_hits":12,"def_int":1,"pass_defended":7,"snaps":870,"snap_share":0.753},"percentiles":{"tackles_solo":80.8,"tackles":95.0,"tfl":50.0,"def_sacks":25.0,"qb_hits":70.0,"def_int":95.0,"pass_defended":95.0,"snaps":95.0,"snap_share":86.1}},{"season":2023,"team":"CAR","teams":["CAR"],"pos":"DL","games":17,"game_type":"REG","stats":{"tackles_solo":47,"tackles":93,"tfl":7,"def_sacks":2.0,"qb_hits":15,"def_int":1,"pass_defended":6,"snaps":940,"snap_share":0.891},"percentiles":{"tackles_solo":95.0,"tackles":95.0,"tfl":68.8,"def_sacks":37.5,"qb_hits":78.9,"def_int":95.0,"pass_defended":95.0,"snaps":95.0,"snap_share":95.0}},{"season":2024,"team":"CAR","teams":["CAR"],"pos":"DL","games":1,"game_type":"REG","stats":{"tackles":2,"snaps":60,"snap_share":0.909},"percentiles":{}},{"season":2025,"team":"CAR","teams":["CAR"],"pos":"DL","games":17,"game_type":"REG","stats":{"tackles_solo":32,"tackles":72,"tfl":5,"def_sacks":5.0,"qb_hits":11,"pass_defended":7,"ff":1,"snaps":808,"snap_share":0.765},"percentiles":{"tackles_solo":95.0,"tackles":95.0,"tfl":58.3,"def_sacks":80.0,"qb_hits":77.5,"pass_defended":95.0,"ff":75.0,"snaps":95.0,"snap_share":95.0}},{"season":2025,"team":"CAR","teams":["CAR"],"pos":"DL","games":1,"game_type":"POST","stats":{"tackles_solo":4,"tackles":5,"qb_hits":1,"snaps":73,"snap_share":0.961},"percentiles":{}}],"career":{"games":84,"stats":{"tackles_solo":147,"tackles":299,"tfl":33,"def_sacks":13.0,"qb_hits":59,"pass_defended":28,"snaps":4052,"def_int":2,"ff":1}},"career_post":{"games":1,"stats":{"tackles_solo":4,"tackles":5,"qb_hits":1,"snaps":73}},"game_logs":[{"season":2020,"week":1,"game_type":"REG","date":"2020-09-13","team":"CAR","opp":"LV","home":true,"stats":{"tackles_solo":1,"tackles":2,"tfl":1,"pass_defended":2}},{"season":2020,"week":2,"game_type":"REG","date":"2020-09-20","team":"CAR","opp":"TB","home":false,"stats":{"tackles_solo":1,"tackles":1}},{"season":2020,"week":3,"game_type":"REG","date":"2020-09-27","team":"CAR","opp":"LAC","home":false,"stats":{"tackles_solo":3,"tackles":4,"tfl":3}},{"season":2020,"week":4,"game_type":"REG","date":"2020-10-04","team":"CAR","opp":"ARI","home":true,"stats":{"tackles_solo":2,"tackles":2,"tfl":1}},{"season":2020,"week":6,"game_type":"REG","date":"2020-10-18","team":"CAR","opp":"CHI","home":true,"stats":{"tackles_solo":2,"tackles":3,"tfl":1,"qb_hits":1}},{"season":2020,"week":7,"game_type":"REG","date":"2020-10-25","team":"CAR","opp":"NO","home":false,"stats":{"tackles":1}},{"season":2020,"week":8,"game_type":"REG","date":"2020-10-29","team":"CAR","opp":"ATL","home":true,"stats":{"tackles_solo":1,"tackles":4}},{"season":2020,"week":9,"game_type":"REG","date":"2020-11-08","team":"CAR","opp":"KC","home":false,"stats":{"tackles_solo":3,"tackles":4,"qb_hits":1}},{"season":2020,"week":10,"game_type":"REG","date":"2020-11-15","team":"CAR","opp":"TB","home":true,"stats":{"tackles_solo":1,"tackles":3,"qb_hits":1}},{"season":2020,"week":11,"game_type":"REG","date":"2020-11-22","team":"CAR","opp":"DET","home":true,"stats":{"qb_hits":2}},{"season":2020,"week":12,"game_type":"REG","date":"2020-11-29","team":"CAR","opp":"MIN","home":false,"stats":{"tackles_solo":1,"tackles":2,"qb_hits":2}},{"season":2020,"week":14,"game_type":"REG","date":"2020-12-13","team":"CAR","opp":"DEN","home":true,"stats":{"tackles_solo":1,"tackles":2,"qb_hits":1}},{"season":2020,"week":15,"game_type":"REG","date":"2020-12-19","team":"CAR","opp":"GB","home":false,"stats":{"tackles_solo":3,"tackles":3,"tfl":2,"def_sacks":2.0,"qb_hits":2}},{"season":2020,"week":16,"game_type":"REG","date":"2020-12-27","team":"CAR","opp":"WAS","home":false,"stats":{"tackles_solo":1,"tackles":1,"qb_hits":1,"pass_defended":2}},{"season":2020,"week":17,"game_type":"REG","date":"2021-01-03","team":"CAR","opp":"NO","home":true,"stats":{"tackles":1,"qb_hits":1}},{"season":2021,"week":1,"game_type":"REG","date":"2021-09-12","team":"CAR","opp":"NYJ","home":true,"stats":{"tackles_solo":2,"tackles":4,"tfl":1,"def_sacks":1.0,"qb_hits":1,"pass_defended":1}},{"season":2021,"week":2,"game_type":"REG","date":"2021-09-19","team":"CAR","opp":"NO","home":true,"stats":{"tackles_solo":1,"tackles":1}},{"season":2021,"week":3,"game_type":"REG","date":"2021-09-23","team":"CAR","opp":"HOU","home":false,"stats":{"tackles_solo":2,"tackles":2,"tfl":1}},{"season":2021,"week":4,"game_type":"REG","date":"2021-10-03","team":"CAR","opp":"DAL","home":false,"stats":{"tackles_solo":1,"tackles":1}},{"season":2021,"week":5,"game_type":"REG","date":"2021-10-10","team":"CAR","opp":"PHI","home":true,"stats":{"tackles_solo":1,"tackles":3,"pass_defended":1}},{"season":2021,"week":6,"game_type":"REG","date":"2021-10-17","team":"CAR","opp":"MIN","home":true,"stats":{"tackles_solo":1,"tackles":2,"qb_hits":1}},{"season":2021,"week":7,"game_type":"REG","date":"2021-10-24","team":"CAR","opp":"NYG","home":false,"stats":{"tackles_solo":2,"tackles":4,"tfl":2,"def_sacks":1.0,"qb_hits":1}},{"season":2021,"week":8,"game_type":"REG","date":"2021-10-31","team":"CAR","opp":"ATL","home":false,"stats":{"tackles_solo":2,"tackles":2,"qb_hits":1,"pass_defended":1}},{"season":2021,"week":9,"game_type":"REG","date":"2021-11-07","team":"CAR","opp":"NE","home":true,"stats":{"tackles_solo":1,"tackles":3,"pass_defended":1}},{"season":2021,"week":10,"game_type":"REG","date":"2021-11-14","team":"CAR","opp":"ARI","home":false,"stats":{"tackles_solo":1,"tackles":2,"qb_hits":1}},{"season":2021,"week":11,"game_type":"REG","date":"2021-11-21","team":"CAR","opp":"WAS","home":true,"stats":{"tackles_solo":1,"tackles":2}},{"season":2021,"week":12,"game_type":"REG","date":"2021-11-28","team":"CAR","opp":"MIA","home":false,"stats":{"tackles_solo":1,"tackles":2}},{"season":2021,"week":14,"game_type":"REG","date":"2021-12-12","team":"CAR","opp":"ATL","home":true,"stats":{"tackles_solo":4,"tackles":5,"tfl":2,"qb_hits":2}},{"season":2021,"week":16,"game_type":"REG","date":"2021-12-26","team":"CAR","opp":"TB","home":true,"stats":{"tackles":1}},{"season":2021,"week":17,"game_type":"REG","date":"2022-01-02","team":"CAR","opp":"NO","home":false,"stats":{"tackles_solo":3,"tackles":3,"tfl":2,"def_sacks":1.0,"qb_hits":1}},{"season":2021,"week":18,"game_type":"REG","date":"2022-01-09","team":"CAR","opp":"TB","home":false,"stats":{"tackles_solo":1,"tackles":1,"qb_hits":1}},{"season":2022,"week":1,"game_type":"REG","date":"2022-09-11","team":"CAR","opp":"CLE","home":true,"stats":{"tackles_solo":1,"tackles":5}},{"season":2022,"week":2,"game_type":"REG","date":"2022-09-18","team":"CAR","opp":"NYG","home":false,"stats":{"tackles":3,"qb_hits":1,"pass_defended":1}},{"season":2022,"week":3,"game_type":"REG","date":"2022-09-25","team":"CAR","opp":"NO","home":true,"stats":{"tackles_solo":1,"tackles":1,"def_int":1,"pass_defended":2}},{"season":2022,"week":4,"game_type":"REG","date":"2022-10-02","team":"CAR","opp":"ARI","home":true,"stats":{"tackles_solo":1,"tackles":1,"pass_defended":1}},{"season":2022,"week":5,"game_type":"REG","date":"2022-10-09","team":"CAR","opp":"SF","home":true,"stats":{"tackles_solo":2,"tackles":4,"tfl":1,"pass_defended":2}},{"season":2022,"week":6,"game_type":"REG","date":"2022-10-16","team":"CAR","opp":"LA","home":false,"stats":{"tackles_solo":3,"tackles":7,"def_sacks":0.5,"qb_hits":2}},{"season":2022,"week":7,"game_type":"REG","date":"2022-10-23","team":"CAR","opp":"TB","home":true,"stats":{"tackles_solo":3,"tackles":4,"qb_hits":1}},{"season":2022,"week":8,"game_type":"REG","date":"2022-10-30","team":"CAR","opp":"ATL","home":false,"stats":{"tackles_solo":3,"tackles":10,"tfl":1,"def_sacks":0.5,"qb_hits":1}},{"season":2022,"week":9,"game_type":"REG","date":"2022-11-06","team":"CAR","opp":"CIN","home":false,"stats":{"tackles":2}},{"season":2022,"week":10,"game_type":"REG","date":"2022-11-10","team":"CAR","opp":"ATL","home":true,"stats":{"tackles_solo":2,"tackles":6,"tfl":2}},{"season":2022,"week":11,"game_type":"REG","date":"2022-11-20","team":"CAR","opp":"BAL","home":false,"stats":{"tackles_solo":1,"tackles":1,"tfl":1}},{"season":2022,"week":12,"game_type":"REG","date":"2022-11-27","team":"CAR","opp":"DEN","home":true,"stats":{"tackles_solo":1,"tackles":1,"qb_hits":1}},{"season":2022,"week":15,"game_type":"REG","date":"2022-12-18","team":"CAR","opp":"PIT","home":true,"stats":{"tackles_solo":2,"tackles":5,"qb_hits":1}},{"season":2022,"week":16,"game_type":"REG","date":"2022-12-24","team":"CAR","opp":"DET","home":true,"stats":{"tackles":1,"qb_hits":1,"pass_defended":1}},{"season":2022,"week":17,"game_type":"REG","date":"2023-01-01","team":"CAR","opp":"TB","home":false,"stats":{"tackles_solo":2,"tackles":3,"qb_hits":2}},{"season":2022,"week":18,"game_type":"REG","date":"2023-01-08","team":"CAR","opp":"NO","home":false,"stats":{"tackles_solo":2,"tackles":7,"qb_hits":2}},{"season":2023,"week":1,"game_type":"REG","date":"2023-09-10","team":"CAR","opp":"ATL","home":false,"stats":{"tackles_solo":5,"tackles":5,"tfl":2,"def_sacks":1.0,"qb_hits":1}},{"season":2023,"week":2,"game_type":"REG","date":"2023-09-18","team":"CAR","opp":"NO","home":true,"stats":{"tackles_solo":4,"tackles":7}},{"season":2023,"week":3,"game_type":"REG","date":"2023-09-24","team":"CAR","opp":"SEA","home":false,"stats":{"tackles_solo":3,"tackles":5,"qb_hits":2}},{"season":2023,"week":4,"game_type":"REG","date":"2023-10-01","team":"CAR","opp":"MIN","home":true,"stats":{"tackles":3}},{"season":2023,"week":5,"game_type":"REG","date":"2023-10-08","team":"CAR","opp":"DET","home":false,"stats":{"tackles_solo":2,"tackles":6,"qb_hits":2}},{"season":2023,"week":6,"game_type":"REG","date":"2023-10-15","team":"CAR","opp":"MIA","home":false,"stats":{"tackles":1}},{"season":2023,"week":8,"game_type":"REG","date":"2023-10-29","team":"CAR","opp":"HOU","home":true,"stats":{"tackles_solo":2,"tackles":5,"pass_defended":1}},{"season":2023,"week":9,"game_type":"REG","date":"2023-11-05","team":"CAR","opp":"IND","home":true,"stats":{"tackles_solo":2,"tackles":4,"qb_hits":1,"pass_defended":1}},{"season":2023,"week":10,"game_type":"REG","date":"2023-11-09","team":"CAR","opp":"CHI","home":false,"stats":{"tackles_solo":7,"tackles":8,"tfl":2,"qb_hits":2}},{"season":2023,"week":11,"game_type":"REG","date":"2023-11-19","team":"CAR","opp":"DAL","home":true,"stats":{"tackles_solo":3,"tackles":5,"tfl":1,"qb_hits":1}},{"season":2023,"week":12,"game_type":"REG","date":"2023-11-26","team":"CAR","opp":"TEN","home":false,"stats":{"tackles_solo":2,"tackles":5,"tfl":1,"pass_defended":1}},{"season":2023,"week":13,"game_type":"REG","date":"2023-12-03","team":"CAR","opp":"TB","home":false,"stats":{"tackles_solo":1,"tackles":4,"qb_hits":2}},{"season":2023,"week":14,"game_type":"REG","date":"2023-12-10","team":"CAR","opp":"NO","home":false,"stats":{"tackles_solo":5,"tackles":10,"qb_hits":1,"def_int":1,"pass_defended":1}},{"season":2023,"week":15,"game_type":"REG","date":"2023-12-17","team":"CAR","opp":"ATL","home":true,"stats":{"tackles_solo":1,"tackles":4,"qb_hits":1}},{"season":2023,"week":16,"game_type":"REG","date":"2023-12-24","team":"CAR","opp":"GB","home":true,"stats":{"tackles_solo":3,"tackles":8}},{"season":2023,"week":17,"game_type":"REG","date":"2023-12-31","team":"CAR","opp":"JAX","home":false,"stats":{"tackles_solo":2,"tackles":7,"pass_defended":1}},{"season":2023,"week":18,"game_type":"REG","date":"2024-01-07","team":"CAR","opp":"TB","home":true,"stats":{"tackles_solo":5,"tackles":6,"tfl":1,"def_sacks":1.0,"qb_hits":2,"pass_defended":1}},{"season":2024,"week":1,"game_type":"REG","date":"2024-09-08","team":"CAR","opp":"NO","home":false,"stats":{"tackles":2}},{"season":2025,"week":1,"game_type":"REG","date":"2025-09-07","team":"CAR","opp":"JAX","home":false,"stats":{"tackles_solo":3,"tackles":4}},{"season":2025,"week":2,"game_type":"REG","date":"2025-09-14","team":"CAR","opp":"ARI","home":false,"stats":{"tackles_solo":3,"tackles":3,"qb_hits":1,"pass_defended":2}},{"season":2025,"week":3,"game_type":"REG","date":"2025-09-21","team":"CAR","opp":"ATL","home":true,"stats":{"tackles_solo":1,"tackles":2,"qb_hits":1}},{"season":2025,"week":4,"game_type":"REG","date":"2025-09-28","team":"CAR","opp":"NE","home":false,"stats":{"tackles_solo":1,"tackles":4}},{"season":2025,"week":5,"game_type":"REG","date":"2025-10-05","team":"CAR","opp":"MIA","home":true,"stats":{"tackles_solo":1,"tackles":3,"tfl":1,"def_sacks":1.0,"qb_hits":1}},{"season":2025,"week":6,"game_type":"REG","date":"2025-10-12","team":"CAR","opp":"DAL","home":true,"stats":{"tackles_solo":2,"tackles":3,"tfl":1,"qb_hits":1}},{"season":2025,"week":7,"game_type":"REG","date":"2025-10-19","team":"CAR","opp":"NYJ","home":false,"stats":{"tackles_solo":4,"tackles":7,"def_sacks":2.0,"qb_hits":3,"pass_defended":3}},{"season":2025,"week":8,"game_type":"REG","date":"2025-10-26","team":"CAR","opp":"BUF","home":true,"stats":{"tackles":1}},{"season":2025,"week":9,"game_type":"REG","date":"2025-11-02","team":"CAR","opp":"GB","home":false,"stats":{"tackles_solo":2,"tackles":4,"qb_hits":1}},{"season":2025,"week":10,"game_type":"REG","date":"2025-11-09","team":"CAR","opp":"NO","home":true,"stats":{"tackles_solo":2,"tackles":8,"tfl":1}},{"season":2025,"week":12,"game_type":"REG","date":"2025-11-24","team":"CAR","opp":"SF","home":false,"stats":{"tackles":3,"pass_defended":1}},{"season":2025,"week":13,"game_type":"REG","date":"2025-11-30","team":"CAR","opp":"LA","home":true,"stats":{"tackles_solo":1,"tackles":2,"tfl":1,"def_sacks":1.0,"qb_hits":1,"pass_defended":1,"ff":1}},{"season":2025,"week":15,"game_type":"REG","date":"2025-12-14","team":"CAR","opp":"NO","home":false,"stats":{"tackles_solo":1,"tackles":4}},{"season":2025,"week":16,"game_type":"REG","date":"2025-12-21","team":"CAR","opp":"TB","home":true,"stats":{"tackles_solo":3,"tackles":5,"tfl":1,"def_sacks":1.0,"qb_hits":1}},{"season":2025,"week":17,"game_type":"REG","date":"2025-12-28","team":"CAR","opp":"SEA","home":true,"stats":{"tackles_solo":3,"tackles":6,"qb_hits":1}},{"season":2025,"week":18,"game_type":"REG","date":"2026-01-03","team":"CAR","opp":"TB","home":false,"stats":{"tackles_solo":5,"tackles":13}},{"season":2025,"week":19,"game_type":"WC","date":"2026-01-10","team":"CAR","opp":"LA","home":true,"stats":{"tackles_solo":4,"tackles":5,"qb_hits":1}}]}
